openbb_fixedincome/__init__.py
openbb_fixedincome/corporate/__init__.py
openbb_fixedincome/corporate/corporate_router.py
openbb_fixedincome/fixedincome_router.py
openbb_fixedincome/fixedincome_views.py
openbb_fixedincome/government/__init__.py
openbb_fixedincome/government/government_router.py
openbb_fixedincome/py.typed
openbb_fixedincome/rate/__init__.py
openbb_fixedincome/rate/rate_router.py
openbb_fixedincome/spreads/__init__.py
openbb_fixedincome/spreads/spreads_router.py
openbb_fixedincome-1.4.3.dist-info/METADATA
openbb_fixedincome-1.4.3.dist-info/WHEEL
openbb_fixedincome-1.4.3.dist-info/entry_points.txt
openbb_fixedincome-1.4.3.dist-info/RECORD
